README.rst
setup.py
pomop/__init__.py
pomop/pomop.py
pomop.egg-info/PKG-INFO
pomop.egg-info/SOURCES.txt
pomop.egg-info/dependency_links.txt
pomop.egg-info/entry_points.txt
pomop.egg-info/top_level.txt