Metadata-Version: 1.1
Name: pomop
Version: 0.1.8
Summary: (Poor man) pomodoro technique for productivity
Home-page: https://github.com/hvnsweeting/pomop
Author: Viet Hung Nguyen
Author-email: hvn@familug.org
License: MIT
Platform: UNKNOWN
Classifier: Environment :: Console
